compysitions/__init__.py
compysitions/compysitions.py
compysitions-0.0.3.dist-info/LICENSE
compysitions-0.0.3.dist-info/METADATA
compysitions-0.0.3.dist-info/WHEEL
compysitions-0.0.3.dist-info/top_level.txt
compysitions-0.0.3.dist-info/RECORD
