Metadata-Version: 2.1
Name: compysitions
Version: 0.0.3
Summary: Extensions for working with Python Dataclasses
Home-page: https://github.com/zganger/compysitions
Author: zganger
Author-email: zganger@icloud.com
License-File: LICENSE
